xnv/__init__.py
xnv/__main__.py
xnv/daemon.py
xnv/utils.py
xnv/wallet.py
pyxnv-1.0.0a3.dist-info/LICENSE
pyxnv-1.0.0a3.dist-info/METADATA
pyxnv-1.0.0a3.dist-info/WHEEL
pyxnv-1.0.0a3.dist-info/RECORD
