Metadata-Version: 2.1
Name: pyxnv
Version: 1.0.0a3
Summary: Python bindings for the JSON RPC interface of the Nerva cryptocurrency.
Home-page: https://github.com/Sn1F3rt/pyxnv
License: MIT
Keywords: nerva,cryptocurrency,json-rpc,bindings,python
Author: Sayan Bhattacharyya
Author-email: sayan@sn1f3rt.dev
Requires-Python: >=3.8,<4.0
Classifier: Development Status :: 3 - Alpha
Classifier: Intended Audience :: Developers
Classifier: License :: OSI Approved :: MIT License
Classifier: Operating System :: OS Independent
Classifier: Programming Language :: Python :: 3
Classifier: Programming Language :: Python :: 3.8
Classifier: Programming Language :: Python :: 3.9
Classifier: Programming Language :: Python :: 3.10
Classifier: Programming Language :: Python :: 3.11
Classifier: Programming Language :: Python :: 3.12
Classifier: Topic :: Software Development :: Libraries :: Python Modules
Requires-Dist: aiohttp (>=3.10.5,<4.0.0)
Project-URL: Documentation, https://github.com/Sn1F3rt/pyxnv?tab=readme-ov-file#documentation
Project-URL: Repository, https://github.com/Sn1F3rt/pyxnv
